cnpjinfo/__init__.py
cnpjinfo-0.0.3.dist-info/LICENSE.txt
cnpjinfo-0.0.3.dist-info/METADATA
cnpjinfo-0.0.3.dist-info/WHEEL
cnpjinfo-0.0.3.dist-info/top_level.txt
cnpjinfo-0.0.3.dist-info/RECORD
